s3os/__init__.py
s3os/api.py
s3os/encoding.py
s3os/s3_dict.py
s3os/s3_wrapper.py
s3os-1.0.0.dist-info/LICENSE
s3os-1.0.0.dist-info/WHEEL
s3os-1.0.0.dist-info/METADATA
s3os-1.0.0.dist-info/RECORD
