Metadata-Version: 2.1
Name: s3os
Version: 1.0.0
Summary: S3 Object Store. Store and retrieve python objects in s3 simply..
Home-page: https://github.com/MartinHowarth/s3os
License: MIT
Author: Martin Howarth
Author-email: howarth.martin@gmail.com
Requires-Python: >=3.8,<4.0
Classifier: License :: OSI Approved :: MIT License
Classifier: Programming Language :: Python :: 3
Classifier: Programming Language :: Python :: 3.8
Requires-Dist: boto3 (>=1.10.50,<2.0.0)
Requires-Dist: ruamel.yaml (>=0.16.5,<0.17.0)
Requires-Dist: toml (>=0.9,<0.10)
Project-URL: Repository, https://github.com/MartinHowarth/s3os
